litewebagent/__init__.py
litewebagent/action/__init__.py
litewebagent/action/base.py
litewebagent/action/highlevel.py
litewebagent/action/prompt_functions.py
litewebagent/action/replay.py
litewebagent/action/utils.py
litewebagent/agents/__init__.py
litewebagent/agents/FunctionCallingAgents/BaseAgent.py
litewebagent/agents/FunctionCallingAgents/ContextAwarePlanningAgent.py
litewebagent/agents/FunctionCallingAgents/FunctionCallingAgent.py
litewebagent/agents/FunctionCallingAgents/HighLevelPlanningAgent.py
litewebagent/agents/FunctionCallingAgents/__init__.py
litewebagent/agents/PromptAgents/PromptAgent.py
litewebagent/agents/PromptAgents/__init__.py
litewebagent/agents/SearchAgents/PromptSearchAgent.py
litewebagent/agents/SearchAgents/__init__.py
litewebagent/browser_env/__init__.py
litewebagent/browser_env/constants.py
litewebagent/browser_env/extract_elements.py
litewebagent/browser_env/observation.py
litewebagent/browser_env/javascript/frame_mark_elements.js
litewebagent/browser_env/javascript/frame_unmark_elements.js
litewebagent/core/__init__.py
litewebagent/core/agent_factory.py
litewebagent/evaluation/__init__.py
litewebagent/evaluation/evaluators.py
litewebagent/evaluation/feedback.py
litewebagent/tools/__init__.py
litewebagent/tools/navigation.py
litewebagent/tools/registry.py
litewebagent/tools/select_option.py
litewebagent/tools/shared_utils.py
litewebagent/tools/upload_file.py
litewebagent/tools/webscraping.py
litewebagent/utils/__init__.py
litewebagent/utils/playwright_manager.py
litewebagent/utils/utils.py
litewebagent-0.1.7.dist-info/LICENSE
litewebagent-0.1.7.dist-info/METADATA
litewebagent-0.1.7.dist-info/WHEEL
litewebagent-0.1.7.dist-info/top_level.txt
litewebagent-0.1.7.dist-info/RECORD
