Metadata-Version: 2.1
Name: litewebagent
Version: 0.1.7
Author: Danqing Zhang
Author-email: danqing.zhang.personal@gmail.com
Requires-Python: >=3.6
License-File: LICENSE
Requires-Dist: undetected-playwright ==0.3.0
Requires-Dist: openai ==1.42.0
Requires-Dist: watchdog ==4.0.2
Requires-Dist: python-dotenv ==1.0.1
Requires-Dist: selenium ==4.22.0
Requires-Dist: webdriver-manager ==4.0.1
Requires-Dist: gymnasium ==0.29.1
Requires-Dist: browsergym ==0.4.0
Requires-Dist: pyparsing ==3.1.2
Requires-Dist: browsergym-workarena ==0.3.1
Requires-Dist: litellm ==1.42.1
Requires-Dist: groq ==0.9.0
Requires-Dist: flask ==3.0.3
Requires-Dist: flask-cors ==4.0.1
Requires-Dist: pytablewriter ==1.2.0
Requires-Dist: elevenlabs ==1.6.1
